depy/__init__.py
depy/column_selector.py
depy/summarized_py.py
depy/utils.py
depy/R/impute_missing_values.R
depy/R/limma_trend_dea.R
depy/R/load_example_data.R
depy/R/surrogate_variable_analysis.R
depy/R/vsn_transform.R
summarizedpy-0.4.1.dist-info/licenses/LICENSE
summarizedpy-0.4.1.dist-info/METADATA
summarizedpy-0.4.1.dist-info/WHEEL
summarizedpy-0.4.1.dist-info/top_level.txt
summarizedpy-0.4.1.dist-info/RECORD
