Metadata-Version: 2.4
Name: summarizedpy
Version: 0.4.1
Summary: A differential expression analysis package for proteomics data, which leverages transcriptomics tools.
Author-email: Sebastian Dohm-Hansen <heinrich.sebastian.dohmhansen@gmail.com>
Maintainer-email: Sebastian Dohm-Hansen <heinrich.sebastian.dohmhansen@gmail.com>
License-Expression: MIT
Requires-Python: >=3.11
License-File: LICENSE
Requires-Dist: numpy
Requires-Dist: pandas
Requires-Dist: matplotlib
Requires-Dist: pyarrow
Requires-Dist: adjustText
Requires-Dist: pyjanitor==0.23.1
Requires-Dist: pandas_flavor<0.8
Requires-Dist: openpyxl
Requires-Dist: statsmodels
Requires-Dist: scikit-learn
Provides-Extra: dev
Requires-Dist: jupyter; extra == "dev"
Requires-Dist: pytest; extra == "dev"
Dynamic: license-file
